{
    "title": "vivarent",
    "styles": {
        "fontFamily": "poppins",
        "colors": {
            "primary": "text-blue-500",
            "secondary": "text-green-500",
            "background": "bg-gray-100",
            "border": "border-blue-300"
        },
        "spacing": {
            "padding": {
                "small": "p-2",
                "medium": "p-4",
                "large": "p-6"
            },
            "margin": {
                "small": "m-2",
                "medium": "m-4",
                "large": "m-6"
            }
        },
        "buttons": {
            "primary": {
                "color": "text-white",
                "background": "bg-blue-500",
                "hover": "hover:bg-blue-700"
            },
            "secondary": {
                "color": "text-white",
                "background": "bg-green-500",
                "hover": "hover:bg-green-700"
            }
        }
    },
    "responsive": {
        "breakpoints": {
            "sm": "640px",
            "md": "768px",
            "lg": "1024px",
            "xl": "1280px"
        }
    },
    "ads": {
        "large": {
            "image": {
                "src": "/images/large-ad.jpg",
                "alt": "Large ad showcasing top deals"
            },
            "button": {
                "text": "Shop Now",
                "style": "bg-blue-500 text-white p-4 rounded hover:bg-blue-700"
            },
            "customText": {
                "heading": "Exclusive Deals Await!",
                "description": "Discover amazing products with unbeatable offers.",
                "style": "text-center text-xl font-semibold text-gray-800"
            },
            "style": "w-full h-64 bg-blue-100 text-center flex flex-col justify-center items-center"
        },
        "medium": {
            "image": {
                "src": "/images/medium-ad.jpg",
                "alt": "Medium ad promoting special offers"
            },
            "button": {
                "text": "Learn More",
                "style": "bg-green-500 text-white p-3 rounded hover:bg-green-700"
            },
            "customText": {
                "heading": "Special Offers",
                "description": "Find the best deals on your favorite items.",
                "style": "text-center text-lg font-medium text-gray-700"
            },
            "style": "w-full h-48 bg-green-100 text-center flex flex-col justify-center items-center"
        },
        "small": {
            "image": {
                "src": "/images/small-ad.jpg",
                "alt": "Small ad for targeted promotions"
            },
            "button": {
                "text": "Explore",
                "style": "bg-yellow-500 text-white p-2 rounded hover:bg-yellow-700"
            },
            "customText": {
                "heading": "Compact Ad Space",
                "description": "Ideal for showcasing smaller promotions.",
                "style": "text-center text-md font-regular text-gray-600"
            },
            "style": "w-full h-32 bg-yellow-100 text-center flex flex-col justify-center items-center"
        },
        "lengthy": {
            "image": {
                "src": "/images/lengthy-ad.jpg",
                "alt": "Lengthy ad for detailed visuals"
            },
            "button": {
                "text": "View Details",
                "style": "bg-gray-500 text-white p-4 rounded hover:bg-gray-700"
            },
            "customText": {
                "heading": "Detailed Promotion",
                "description": "Provide an in-depth look at your products or services.",
                "style": "text-left text-lg font-light text-gray-800"
            },
            "style": "w-full bg-gray-100 text-left flex flex-col justify-start items-start p-6"
        }
    },
    "aboutUs": {
        "heading": {
            "text": "About Us",
            "style": "text-3xl font-bold text-center text-blue-600"
        },
        "description": {
            "text": "Vivarent is your trusted platform for connecting renters and owners. Our mission is to make renting seamless and accessible for everyone.",
            "style": "text-lg text-center text-gray-700"
        }
    },
    "popularCategory": {
        "heading": {
            "text": "Popular Categories",
            "style": "text-3xl font-semibold text-left text-blue-600"
        }
    },
    "bestWeeklyDeals": {
        "heading": {
            "text": "Best Weekly Deals",
            "style": "text-3xl font-semibold text-left text-green-600"
        }
    },
    "trendingSearch": {
        "heading": {
            "text": "Trending Searches",
            "style": "text-3xl font-semibold text-left text-purple-600"
        }
    },
    "popularSellers": {
        "heading": {
            "text": "Popular Sellers",
            "style": "text-3xl font-semibold text-left text-orange-600"
        }
    },
    "hotCollections": {
        "heading": {
            "text": "Hot Collections",
            "style": "text-3xl font-semibold text-left text-red-600"
        }
    },
    "listYourProduct": {
        "heading": {
            "text": "List Your Product",
            "style": "text-3xl font-semibold text-left text-blue-600"
        }
    }
}
